{
  "id": "git-unstage-file",
  "command": "git reset <file>",
  "description": "Remove one file from the staging area without changing it on disk",
  "tool": "git",
  "category": "staging",
  "tags": [
    "unstage",
    "remove from index",
    "take out of commit"
  ],
  "intents": [
    "i staged a file by mistake and want to take it out",
    "remove a file from the staging area",
    "unstage just one file without losing my edits",
    "i dont want this file in my next commit anymore",
    "i changed my mind about staging this file and want to drop it",
    "take a file back out of the index after git add",
    "undo a git add for one specific file",
    "exclude a file from the commit i am about to make"
  ],
  "example": "git reset src/secrets.js",
  "danger": false,
  "related": [
    "git-unstage-all",
    "git-add-file"
  ]
}
